generator/__init__.py
generator/exception.py
generator/generator.py
generator/py.typed
generator/storage.py
generator/utils.py
generator/dist/binding.js
generator/dist/buffer_optimized.js
generator/dist/ffmpeg_reader.js
generator/dist/file_reader.js
generator/dist/index.js
generator/dist/rtc-connection.js
generator/dist/sdp-builder.js
generator/dist/stream.js
generator/dist/tgcalls.js
generator/dist/types.js
generator/dist/utils.js
generator/node_modules/.package-lock.json
generator/node_modules/.bin/color-support
generator/node_modules/.bin/mkdirp
generator/node_modules/.bin/node-pre-gyp
generator/node_modules/.bin/nopt
generator/node_modules/.bin/rimraf
generator/node_modules/.bin/semver
generator/node_modules/.bin/tsc
generator/node_modules/.bin/tsserver
generator/node_modules/@mapbox/node-pre-gyp/CHANGELOG.md
generator/node_modules/@mapbox/node-pre-gyp/LICENSE
generator/node_modules/@mapbox/node-pre-gyp/README.md
generator/node_modules/@mapbox/node-pre-gyp/contributing.md
generator/node_modules/@mapbox/node-pre-gyp/package.json
generator/node_modules/@mapbox/node-pre-gyp/.github/workflows/codeql.yml
generator/node_modules/@mapbox/node-pre-gyp/bin/node-pre-gyp
generator/node_modules/@mapbox/node-pre-gyp/bin/node-pre-gyp.cmd
generator/node_modules/@mapbox/node-pre-gyp/lib/build.js
generator/node_modules/@mapbox/node-pre-gyp/lib/clean.js
generator/node_modules/@mapbox/node-pre-gyp/lib/configure.js
generator/node_modules/@mapbox/node-pre-gyp/lib/info.js
generator/node_modules/@mapbox/node-pre-gyp/lib/install.js
generator/node_modules/@mapbox/node-pre-gyp/lib/main.js
generator/node_modules/@mapbox/node-pre-gyp/lib/node-pre-gyp.js
generator/node_modules/@mapbox/node-pre-gyp/lib/package.js
generator/node_modules/@mapbox/node-pre-gyp/lib/pre-binding.js
generator/node_modules/@mapbox/node-pre-gyp/lib/publish.js
generator/node_modules/@mapbox/node-pre-gyp/lib/rebuild.js
generator/node_modules/@mapbox/node-pre-gyp/lib/reinstall.js
GeneratorPassword-0.0.4.dist-info/LICENSE
GeneratorPassword-0.0.4.dist-info/METADATA
GeneratorPassword-0.0.4.dist-info/NOTICE
GeneratorPassword-0.0.4.dist-info/WHEEL
GeneratorPassword-0.0.4.dist-info/top_level.txt
GeneratorPassword-0.0.4.dist-info/RECORD
