Metadata-Version: 2.1
Name: GeneratorPassword
Version: 0.0.4
Summary: GeneratorPassword - Random password generator Library for Python.
Home-page: https://github.com/AyiinXd/GeneratorPassword
Author: AyiinXd
Author-email: ayingaming98@gmail.com
License: GNU Affero General Public License v3.0 (AGPL-3.0)
Project-URL: Bug Tracker, https://github.com/AyiinXd/GeneratorPassword/issues
Project-URL: Documentation, https://generator_password.tech
Project-URL: Source Code, https://github.com/AyiinXd/GeneratorPassword
Classifier: Programming Language :: Python :: 3
Classifier: Programming Language :: Python :: 3.8
Classifier: Programming Language :: Python :: 3.9
Classifier: Programming Language :: Python :: 3.10
Classifier: License :: OSI Approved :: GNU General Public License v3 (GPLv3)
Classifier: Operating System :: OS Independent
Requires-Python: ~=3.7
License-File: LICENSE
License-File: NOTICE
Requires-Dist: aiohttp ==3.8.5
Requires-Dist: html2text
Requires-Dist: requests
